termtosvg/__init__.py
termtosvg/__main__.py
termtosvg/anim.py
termtosvg/asciicast.py
termtosvg/config.py
termtosvg/main.py
termtosvg/term.py
termtosvg/data/svg11-flat-20110816.dtd
termtosvg/data/templates/base16_default_dark.svg
termtosvg/data/templates/dracula.svg
termtosvg/data/templates/gjm8.svg
termtosvg/data/templates/gjm8_play.svg
termtosvg/data/templates/gjm8_single_loop.svg
termtosvg/data/templates/powershell.svg
termtosvg/data/templates/progress_bar.svg
termtosvg/data/templates/putty.svg
termtosvg/data/templates/solarized_dark.svg
termtosvg/data/templates/solarized_light.svg
termtosvg/data/templates/terminal_app.svg
termtosvg/data/templates/ubuntu.svg
termtosvg/data/templates/window_frame.svg
termtosvg/data/templates/window_frame_js.svg
termtosvg/data/templates/window_frame_powershell.svg
termtosvg/data/templates/xterm.svg
termtosvg/tests/__init__.py
termtosvg/tests/suite.py
termtosvg/tests/test_anim.py
termtosvg/tests/test_asciicast.py
termtosvg/tests/test_config.py
termtosvg/tests/test_main.py
termtosvg/tests/test_term.py
termtosvg-1.1.0.data/scripts/termtosvg
termtosvg-1.1.0.dist-info/LICENSE
termtosvg-1.1.0.dist-info/METADATA
termtosvg-1.1.0.dist-info/WHEEL
termtosvg-1.1.0.dist-info/top_level.txt
termtosvg-1.1.0.dist-info/RECORD
